<?xml version='1.0' encoding='UTF-16' standalone='yes' ?>
<units>
  <unit>
    <title>Lighthouse 4 Unit 1</title>
    <vocables>
      <vocable>
        <first_meaning>
          <value>immigrant</value>
        </first_meaning>
        <second_meaning>
          <value>Einwanderer</value>
        </second_meaning>
      </vocable>
      <vocable>
        <first_meaning>
          <value>alligator</value>
        </first_meaning>
        <second_meaning>
          <value>Alligator</value>
        </second_meaning>
      </vocable>
      <vocable>
        <first_meaning>
          <value>buffalo</value>
        </first_meaning>
        <second_meaning>
          <value>Büffel; Bison</value>
        </second_meaning>
      </vocable>
      <vocable>
        <first_meaning>
          <value>nature</value>
        </first_meaning>
        <second_meaning>
          <value>Natur</value>
        </second_meaning>
      </vocable>
      <vocable>
        <first_meaning>
          <value>star</value>
        </first_meaning>
        <second_meaning>
          <value>Stern</value>
        </second_meaning>
      </vocable>
      <vocable>
        <first_meaning>
          <value>state</value>
        </first_meaning>
        <second_meaning>
          <value>Bundesstaat</value>
        </second_meaning>
      </vocable>
      <vocable>
        <first_meaning>
          <value>Native American</value>
        </first_meaning>
        <second_meaning>
          <value>amerikanischer Ureinwohner</value>
        </second_meaning>
      </vocable>
      <vocable>
        <first_meaning>
          <value>slave</value>
        </first_meaning>
        <second_meaning>
          <value>Sklave</value>
        </second_meaning>
      </vocable>
      <vocable>
        <first_meaning>
          <value>European</value>
        </first_meaning>
        <second_meaning>
          <value>Europäer</value>
        </second_meaning>
      </vocable>
      <vocable>
        <first_meaning>
          <value>settler</value>
        </first_meaning>
        <second_meaning>
          <value>Siedler</value>
        </second_meaning>
      </vocable>
      <vocable>
        <first_meaning>
          <value>fight</value>
        </first_meaning>
        <second_meaning>
          <value>kämpfen</value>
        </second_meaning>
      </vocable>
      <vocable>
        <first_meaning>
          <value>war</value>
        </first_meaning>
        <second_meaning>
          <value>Krieg</value>
        </second_meaning>
      </vocable>
      <vocable>
        <first_meaning>
          <value>independence</value>
        </first_meaning>
        <second_meaning>
          <value>Unabhängigkeit</value>
        </second_meaning>
      </vocable>
      <vocable>
        <first_meaning>
          <value>hurricane</value>
        </first_meaning>
        <second_meaning>
          <value>Hurrikan</value>
          <value>Orkan</value>
        </second_meaning>
      </vocable>
      <vocable>
        <first_meaning>
          <value>soccer</value>
        </first_meaning>
        <second_meaning>
          <value>Fußball</value>
        </second_meaning>
      </vocable>
      <vocable>
        <first_meaning>
          <value>statue</value>
        </first_meaning>
        <second_meaning>
          <value>Statue</value>
        </second_meaning>
      </vocable>
      <vocable>
        <first_meaning>
          <value>liberty</value>
        </first_meaning>
        <second_meaning>
          <value>Freiheit</value>
        </second_meaning>
      </vocable>
      <vocable>
        <first_meaning>
          <value>freedom</value>
        </first_meaning>
        <second_meaning>
          <value>Freiheit</value>
        </second_meaning>
      </vocable>
      <vocable>
        <first_meaning>
          <value>view</value>
        </first_meaning>
        <second_meaning>
          <value>Aussicht</value>
        </second_meaning>
      </vocable>
      <vocable>
        <first_meaning>
          <value>island</value>
        </first_meaning>
        <second_meaning>
          <value>Insel</value>
        </second_meaning>
      </vocable>
      <vocable>
        <first_meaning>
          <value>skyline</value>
        </first_meaning>
        <second_meaning>
          <value>Skyline</value>
        </second_meaning>
      </vocable>
      <vocable>
        <first_meaning>
          <value>sky</value>
        </first_meaning>
        <second_meaning>
          <value>Himmel</value>
        </second_meaning>
      </vocable>
      <vocable>
        <first_meaning>
          <value>avenue</value>
        </first_meaning>
        <second_meaning>
          <value>Prachtstraße</value>
        </second_meaning>
      </vocable>
      <vocable>
        <first_meaning>
          <value>paradise</value>
        </first_meaning>
        <second_meaning>
          <value>Paradies</value>
        </second_meaning>
      </vocable>
      <vocable>
        <first_meaning>
          <value>awesome</value>
        </first_meaning>
        <second_meaning>
          <value>klasse</value>
        </second_meaning>
      </vocable>
      <vocable>
        <first_meaning>
          <value>skyscraper</value>
        </first_meaning>
        <second_meaning>
          <value>Wolkenkratzer</value>
        </second_meaning>
      </vocable>
      <vocable>
        <first_meaning>
          <value>build</value>
        </first_meaning>
        <second_meaning>
          <value>bauen</value>
        </second_meaning>
      </vocable>
      <vocable>
        <first_meaning>
          <value>destroy</value>
        </first_meaning>
        <second_meaning>
          <value>zerstören</value>
        </second_meaning>
      </vocable>
      <vocable>
        <first_meaning>
          <value>terrorist</value>
        </first_meaning>
        <second_meaning>
          <value>Terrorist</value>
        </second_meaning>
      </vocable>
      <vocable>
        <first_meaning>
          <value>step</value>
        </first_meaning>
        <second_meaning>
          <value>Stufe</value>
        </second_meaning>
      </vocable>
      <vocable>
        <first_meaning>
          <value>crown</value>
        </first_meaning>
        <second_meaning>
          <value>Krone</value>
        </second_meaning>
      </vocable>
      <vocable>
        <first_meaning>
          <value>nose</value>
        </first_meaning>
        <second_meaning>
          <value>Nase</value>
        </second_meaning>
      </vocable>
      <vocable>
        <first_meaning>
          <value>1.6 million</value>
        </first_meaning>
        <second_meaning>
          <value>1,6 Millionen</value>
        </second_meaning>
      </vocable>
      <vocable>
        <first_meaning>
          <value>court</value>
        </first_meaning>
        <second_meaning>
          <value>Spielfeld</value>
        </second_meaning>
      </vocable>
      <vocable>
        <first_meaning>
          <value>playground</value>
        </first_meaning>
        <second_meaning>
          <value>Spielplatz</value>
        </second_meaning>
      </vocable>
      <vocable>
        <first_meaning>
          <value>ice rink</value>
        </first_meaning>
        <second_meaning>
          <value>Schlittschuhbahn</value>
        </second_meaning>
      </vocable>
      <vocable>
        <first_meaning>
          <value>connect</value>
        </first_meaning>
        <second_meaning>
          <value>verbinden</value>
        </second_meaning>
      </vocable>
      <vocable>
        <first_meaning>
          <value>suspension bridge</value>
        </first_meaning>
        <second_meaning>
          <value>Hängebrücke</value>
        </second_meaning>
      </vocable>
      <vocable>
        <first_meaning>
          <value>hang</value>
        </first_meaning>
        <second_meaning>
          <value>hängen</value>
        </second_meaning>
      </vocable>
      <vocable>
        <first_meaning>
          <value>cable</value>
        </first_meaning>
        <second_meaning>
          <value>Drahtseil</value>
        </second_meaning>
      </vocable>
      <vocable>
        <first_meaning>
          <value>after</value>
        </first_meaning>
        <second_meaning>
          <value>nachdem</value>
        </second_meaning>
      </vocable>
      <vocable>
        <first_meaning>
          <value>fact</value>
        </first_meaning>
        <second_meaning>
          <value>Fakt</value>
        </second_meaning>
      </vocable>
      <vocable>
        <first_meaning>
          <value>What else ...?</value>
        </first_meaning>
        <second_meaning>
          <value>Was (sonst) noch ...?</value>
        </second_meaning>
      </vocable>
      <vocable>
        <first_meaning>
          <value>meaning</value>
        </first_meaning>
        <second_meaning>
          <value>Bedeutung</value>
        </second_meaning>
      </vocable>
      <vocable>
        <first_meaning>
          <value>unknown</value>
        </first_meaning>
        <second_meaning>
          <value>unbekannt</value>
        </second_meaning>
      </vocable>
      <vocable>
        <first_meaning>
          <value>context</value>
        </first_meaning>
        <second_meaning>
          <value>(Text-) Zusammenhang</value>
        </second_meaning>
      </vocable>
      <vocable>
        <first_meaning>
          <value>The beach is awesome!</value>
        </first_meaning>
        <second_meaning>
          <value>Der Strand ist großartig!</value>
        </second_meaning>
      </vocable>
      <vocable>
        <first_meaning>
          <value>skyscrapers</value>
        </first_meaning>
        <second_meaning>
          <value>Hochhäuser</value>
        </second_meaning>
      </vocable>
      <vocable>
        <first_meaning>
          <value>immigrants</value>
        </first_meaning>
        <second_meaning>
          <value>Einwanderer</value>
        </second_meaning>
      </vocable>
      <vocable>
        <first_meaning>
          <value>Sylt is a German island.</value>
        </first_meaning>
        <second_meaning>
          <value>Sylt ist eine deutsche Insel.</value>
        </second_meaning>
      </vocable>
      <vocable>
        <first_meaning>
          <value>mood</value>
        </first_meaning>
        <second_meaning>
          <value>Stimmung</value>
        </second_meaning>
      </vocable>
      <vocable>
        <first_meaning>
          <value>come by</value>
        </first_meaning>
        <second_meaning>
          <value>vorbeikommen</value>
        </second_meaning>
      </vocable>
      <vocable>
        <first_meaning>
          <value>apartment</value>
        </first_meaning>
        <second_meaning>
          <value>Wohnung</value>
        </second_meaning>
      </vocable>
      <vocable>
        <first_meaning>
          <value>That's us.</value>
        </first_meaning>
        <second_meaning>
          <value>Das sind wir.</value>
        </second_meaning>
      </vocable>
      <vocable>
        <first_meaning>
          <value>mom (AE)</value>
        </first_meaning>
        <second_meaning>
          <value>Mama</value>
        </second_meaning>
      </vocable>
      <vocable>
        <first_meaning>
          <value>embarrassing</value>
        </first_meaning>
        <second_meaning>
          <value>peinlich</value>
        </second_meaning>
      </vocable>
      <vocable>
        <first_meaning>
          <value>fall asleep</value>
        </first_meaning>
        <second_meaning>
          <value>einschlafen</value>
        </second_meaning>
      </vocable>
      <vocable>
        <first_meaning>
          <value>be asleep</value>
        </first_meaning>
        <second_meaning>
          <value>schlafen</value>
        </second_meaning>
      </vocable>
      <vocable>
        <first_meaning>
          <value>subway</value>
        </first_meaning>
        <second_meaning>
          <value>U-Bahn</value>
        </second_meaning>
      </vocable>
      <vocable>
        <first_meaning>
          <value>check sth. out</value>
        </first_meaning>
        <second_meaning>
          <value>sich etwas anschauen</value>
        </second_meaning>
      </vocable>
      <vocable>
        <first_meaning>
          <value>diner</value>
        </first_meaning>
        <second_meaning>
          <value>kleines Restaurant</value>
        </second_meaning>
      </vocable>
      <vocable>
        <first_meaning>
          <value>it's way cooler than ...</value>
        </first_meaning>
        <second_meaning>
          <value>es ist viel cooler als ...</value>
        </second_meaning>
      </vocable>
      <vocable>
        <first_meaning>
          <value>title</value>
        </first_meaning>
        <second_meaning>
          <value>Überschrift</value>
        </second_meaning>
      </vocable>
      <vocable>
        <first_meaning>
          <value>chance</value>
        </first_meaning>
        <second_meaning>
          <value>Gelegenheit</value>
        </second_meaning>
      </vocable>
      <vocable>
        <first_meaning>
          <value>choose</value>
        </first_meaning>
        <second_meaning>
          <value>aussuchen</value>
        </second_meaning>
      </vocable>
      <vocable>
        <first_meaning>
          <value>menu</value>
        </first_meaning>
        <second_meaning>
          <value>Speisekarte</value>
        </second_meaning>
      </vocable>
      <vocable>
        <first_meaning>
          <value>recommend sth.</value>
        </first_meaning>
        <second_meaning>
          <value>etwas empfehlen</value>
        </second_meaning>
      </vocable>
      <vocable>
        <first_meaning>
          <value>order (verb)</value>
        </first_meaning>
        <second_meaning>
          <value>bestellen</value>
        </second_meaning>
      </vocable>
      <vocable>
        <first_meaning>
          <value>order (noun)</value>
        </first_meaning>
        <second_meaning>
          <value>Bestellung</value>
        </second_meaning>
      </vocable>
      <vocable>
        <first_meaning>
          <value>extra</value>
        </first_meaning>
        <second_meaning>
          <value>zusätzlich</value>
        </second_meaning>
      </vocable>
      <vocable>
        <first_meaning>
          <value>take</value>
        </first_meaning>
        <second_meaning>
          <value>wegbringen</value>
        </second_meaning>
      </vocable>
      <vocable>
        <first_meaning>
          <value>homeless</value>
        </first_meaning>
        <second_meaning>
          <value>obdachlos</value>
        </second_meaning>
      </vocable>
      <vocable>
        <first_meaning>
          <value>guide</value>
        </first_meaning>
        <second_meaning>
          <value>Ratgeber</value>
        </second_meaning>
      </vocable>
      <vocable>
        <first_meaning>
          <value>rest</value>
        </first_meaning>
        <second_meaning>
          <value>Pause</value>
        </second_meaning>
      </vocable>
      <vocable>
        <first_meaning>
          <value>spelling</value>
        </first_meaning>
        <second_meaning>
          <value>Schreibweise</value>
        </second_meaning>
      </vocable>
      <vocable>
        <first_meaning>
          <value>experience</value>
        </first_meaning>
        <second_meaning>
          <value>erleben</value>
        </second_meaning>
      </vocable>
      <vocable>
        <first_meaning>
          <value>cruise</value>
        </first_meaning>
        <second_meaning>
          <value>Kreuzfahrt</value>
        </second_meaning>
      </vocable>
      <vocable>
        <first_meaning>
          <value>introduction</value>
        </first_meaning>
        <second_meaning>
          <value>Einleitung</value>
        </second_meaning>
      </vocable>
      <vocable>
        <first_meaning>
          <value>crime</value>
        </first_meaning>
        <second_meaning>
          <value>Verbrecher</value>
        </second_meaning>
      </vocable>
      <vocable>
        <first_meaning>
          <value>violence</value>
        </first_meaning>
        <second_meaning>
          <value>Gewalt</value>
        </second_meaning>
      </vocable>
      <vocable>
        <first_meaning>
          <value>suspicious</value>
        </first_meaning>
        <second_meaning>
          <value>verdächtig</value>
        </second_meaning>
      </vocable>
      <vocable>
        <first_meaning>
          <value>innocent</value>
        </first_meaning>
        <second_meaning>
          <value>unschuldig</value>
        </second_meaning>
      </vocable>
      <vocable>
        <first_meaning>
          <value>author</value>
        </first_meaning>
        <second_meaning>
          <value>Autor</value>
        </second_meaning>
      </vocable>
      <vocable>
        <first_meaning>
          <value>trapped</value>
        </first_meaning>
        <second_meaning>
          <value>gefangen</value>
        </second_meaning>
      </vocable>
      <vocable>
        <first_meaning>
          <value>friendship</value>
        </first_meaning>
        <second_meaning>
          <value>Freundschaft</value>
        </second_meaning>
      </vocable>
      <vocable>
        <first_meaning>
          <value>original</value>
        </first_meaning>
        <second_meaning>
          <value>ursprünglich</value>
        </second_meaning>
      </vocable>
      <vocable>
        <first_meaning>
          <value>practice (AE) / practice (BE) (verb)</value>
        </first_meaning>
        <second_meaning>
          <value>üben</value>
        </second_meaning>
      </vocable>
      <vocable>
        <first_meaning>
          <value>practice (noun)</value>
        </first_meaning>
        <second_meaning>
          <value>Training</value>
        </second_meaning>
      </vocable>
      <vocable>
        <first_meaning>
          <value>pull in</value>
        </first_meaning>
        <second_meaning>
          <value>anhalten</value>
        </second_meaning>
      </vocable>
      <vocable>
        <first_meaning>
          <value>get out (of a car)</value>
        </first_meaning>
        <second_meaning>
          <value>aussteigen</value>
        </second_meaning>
      </vocable>
      <vocable>
        <first_meaning>
          <value>sweat</value>
        </first_meaning>
        <second_meaning>
          <value>Schweiß</value>
        </second_meaning>
      </vocable>
      <vocable>
        <first_meaning>
          <value>each other</value>
        </first_meaning>
        <second_meaning>
          <value>einander</value>
        </second_meaning>
      </vocable>
      <vocable>
        <first_meaning>
          <value>cruise</value>
        </first_meaning>
        <second_meaning>
          <value>herumfahren</value>
        </second_meaning>
      </vocable>
      <vocable>
        <first_meaning>
          <value>What's going on?</value>
        </first_meaning>
        <second_meaning>
          <value>Was ist los? / Was gibt's?</value>
        </second_meaning>
      </vocable>
      <vocable>
        <first_meaning>
          <value>as</value>
        </first_meaning>
        <second_meaning>
          <value>als während</value>
        </second_meaning>
      </vocable>
      <vocable>
        <first_meaning>
          <value>routine</value>
        </first_meaning>
        <second_meaning>
          <value>Routine</value>
        </second_meaning>
      </vocable>
      <vocable>
        <first_meaning>
          <value>lean</value>
        </first_meaning>
        <second_meaning>
          <value>lehnen</value>
        </second_meaning>
      </vocable>
      <vocable>
        <first_meaning>
          <value>it might help</value>
        </first_meaning>
        <second_meaning>
          <value>es hilft vielleicht</value>
        </second_meaning>
      </vocable>
      <vocable>
        <first_meaning>
          <value>I guess ...</value>
        </first_meaning>
        <second_meaning>
          <value>ich nehme an</value>
        </second_meaning>
      </vocable>
      <vocable>
        <first_meaning>
          <value>manners (pl)</value>
        </first_meaning>
        <second_meaning>
          <value>Manieren</value>
        </second_meaning>
      </vocable>
      <vocable>
        <first_meaning>
          <value>just</value>
        </first_meaning>
        <second_meaning>
          <value>einfach so</value>
        </second_meaning>
      </vocable>
      <vocable>
        <first_meaning>
          <value>give up</value>
        </first_meaning>
        <second_meaning>
          <value>aufgeben</value>
        </second_meaning>
      </vocable>
      <vocable>
        <first_meaning>
          <value>Who cares?</value>
        </first_meaning>
        <second_meaning>
          <value>Wen interessiert das?</value>
        </second_meaning>
      </vocable>
      <vocable>
        <first_meaning>
          <value>close (to)</value>
        </first_meaning>
        <second_meaning>
          <value>nahe</value>
        </second_meaning>
      </vocable>
      <vocable>
        <first_meaning>
          <value>stare</value>
        </first_meaning>
        <second_meaning>
          <value>starren</value>
        </second_meaning>
      </vocable>
      <vocable>
        <first_meaning>
          <value>to hit</value>
        </first_meaning>
        <second_meaning>
          <value>schlagen</value>
        </second_meaning>
      </vocable>
      <vocable>
        <first_meaning>
          <value>floor</value>
        </first_meaning>
        <second_meaning>
          <value>Fußboden</value>
        </second_meaning>
      </vocable>
      <vocable>
        <first_meaning>
          <value>grow</value>
        </first_meaning>
        <second_meaning>
          <value>(allmählich) werden</value>
        </second_meaning>
      </vocable>
      <vocable>
        <first_meaning>
          <value>fight</value>
        </first_meaning>
        <second_meaning>
          <value>Kampf</value>
        </second_meaning>
      </vocable>
      <vocable>
        <first_meaning>
          <value>turning point</value>
        </first_meaning>
        <second_meaning>
          <value>Wendepunkt</value>
        </second_meaning>
      </vocable>
      <vocable>
        <first_meaning>
          <value>polite</value>
        </first_meaning>
        <second_meaning>
          <value>höflich</value>
        </second_meaning>
      </vocable>
      <vocable>
        <first_meaning>
          <value>floor</value>
        </first_meaning>
        <second_meaning>
          <value>Stockwerk</value>
        </second_meaning>
      </vocable>
      <vocable>
        <first_meaning>
          <value>need to do sth.</value>
        </first_meaning>
        <second_meaning>
          <value>etwas tun müssen</value>
        </second_meaning>
      </vocable>
      <vocable>
        <first_meaning>
          <value>explain sth.</value>
        </first_meaning>
        <second_meaning>
          <value>etwas erklären</value>
        </second_meaning>
      </vocable>
      <vocable>
        <first_meaning>
          <value>the gist</value>
        </first_meaning>
        <second_meaning>
          <value>das Wesentliche</value>
        </second_meaning>
      </vocable>
      <vocable>
        <first_meaning>
          <value>booth</value>
        </first_meaning>
        <second_meaning>
          <value>Nische</value>
          <value>Sitzecke (im Restaurant)</value>
        </second_meaning>
      </vocable>
      <vocable>
        <first_meaning>
          <value>scrambled eggs</value>
        </first_meaning>
        <second_meaning>
          <value>Rühreier</value>
        </second_meaning>
      </vocable>
      <vocable>
        <first_meaning>
          <value>scan a text</value>
        </first_meaning>
        <second_meaning>
          <value>einen Text schnell nach Informationen absuchen</value>
        </second_meaning>
      </vocable>
      <vocable>
        <first_meaning>
          <value>professional</value>
        </first_meaning>
        <second_meaning>
          <value>professionell</value>
        </second_meaning>
      </vocable>
    </vocables>
  </unit>
</units>
